[{"name": "fastcan.FastCanBenchmark.peakmem_fit", "idx": 0, "pretty_name": "fastcan.FastCanBenchmark.peakmem_fit('classif', 'h')", "last_rev": 250, "last_value": 115068928.0, "last_err": 0.0, "prev_value": null, "change_rev": null}, {"name": "fastcan.FastCanBenchmark.peakmem_fit", "idx": 1, "pretty_name": "fastcan.FastCanBenchmark.peakmem_fit('classif', 'eta')", "last_rev": 250, "last_value": 122486784.0, "last_err": 0.0, "prev_value": null, "change_rev": null}, {"name": "fastcan.FastCanBenchmark.peakmem_fit", "idx": 2, "pretty_name": "fastcan.FastCanBenchmark.peakmem_fit('reg', 'h')", "last_rev": 250, "last_value": 162971648.0, "last_err": 0.0, "prev_value": null, "change_rev": null}, {"name": "fastcan.FastCanBenchmark.peakmem_fit", "idx": 3, "pretty_name": "fastcan.FastCanBenchmark.peakmem_fit('reg', 'eta')", "last_rev": 250, "last_value": 213942272.0, "last_err": 0.0, "prev_value": null, "change_rev": null}, {"name": "fastcan.FastCanBenchmark.peakmem_transform", "idx": 0, "pretty_name": "fastcan.FastCanBenchmark.peakmem_transform('classif', 'h')", "last_rev": 250, "last_value": 107655168.0, "last_err": 0.0, "prev_value": null, "change_rev": null}, {"name": "fastcan.FastCanBenchmark.peakmem_transform", "idx": 1, "pretty_name": "fastcan.FastCanBenchmark.peakmem_transform('classif', 'eta')", "last_rev": 250, "last_value": 106868736.0, "last_err": 0.0, "prev_value": null, "change_rev": null}, {"name": "fastcan.FastCanBenchmark.peakmem_transform", "idx": 2, "pretty_name": "fastcan.FastCanBenchmark.peakmem_transform('reg', 'h')", "last_rev": 250, "last_value": 129437696.0, "last_err": 0.0, "prev_value": null, "change_rev": null}, {"name": "fastcan.FastCanBenchmark.peakmem_transform", "idx": 3, "pretty_name": "fastcan.FastCanBenchmark.peakmem_transform('reg', 'eta')", "last_rev": 250, "last_value": 115220480.0, "last_err": 0.0, "prev_value": null, "change_rev": null}, {"name": "fastcan.FastCanBenchmark.time_fit", "idx": 0, "pretty_name": "fastcan.FastCanBenchmark.time_fit('classif', 'h')", "last_rev": 250, "last_value": 0.005010019249997555, "last_err": 0.0, "prev_value": null, "change_rev": null}, {"name": "fastcan.FastCanBenchmark.time_fit", "idx": 1, "pretty_name": "fastcan.FastCanBenchmark.time_fit('classif', 'eta')", "last_rev": 250, "last_value": 0.011193458499995756, "last_err": 0.0, "prev_value": null, "change_rev": null}, {"name": "fastcan.FastCanBenchmark.time_fit", "idx": 2, "pretty_name": "fastcan.FastCanBenchmark.time_fit('reg', 'h')", "last_rev": 250, "last_value": 0.09375565999999225, "last_err": 0.0, "prev_value": null, "change_rev": null}, {"name": "fastcan.FastCanBenchmark.time_fit", "idx": 3, "pretty_name": "fastcan.FastCanBenchmark.time_fit('reg', 'eta')", "last_rev": 250, "last_value": 0.10360582300000232, "last_err": 0.0, "prev_value": null, "change_rev": null}, {"name": "fastcan.FastCanBenchmark.time_transform", "idx": 0, "pretty_name": "fastcan.FastCanBenchmark.time_transform('classif', 'h')", "last_rev": 250, "last_value": 0.00011729963829787888, "last_err": 0.0, "prev_value": null, "change_rev": null}, {"name": "fastcan.FastCanBenchmark.time_transform", "idx": 1, "pretty_name": "fastcan.FastCanBenchmark.time_transform('classif', 'eta')", "last_rev": 250, "last_value": 0.00011648403225809557, "last_err": 0.0, "prev_value": null, "change_rev": null}, {"name": "fastcan.FastCanBenchmark.time_transform", "idx": 2, "pretty_name": "fastcan.FastCanBenchmark.time_transform('reg', 'h')", "last_rev": 250, "last_value": 0.0006024951666666488, "last_err": 0.0, "prev_value": null, "change_rev": null}, {"name": "fastcan.FastCanBenchmark.time_transform", "idx": 3, "pretty_name": "fastcan.FastCanBenchmark.time_transform('reg', 'eta')", "last_rev": 250, "last_value": 0.0006005970588238837, "last_err": 0.0, "prev_value": null, "change_rev": null}, {"name": "fastcan.FastCanBenchmark.track_test_score", "idx": 0, "pretty_name": "fastcan.FastCanBenchmark.track_test_score('classif', 'h')", "last_rev": 250, "last_value": 0.9222222222222223, "last_err": 0.0, "prev_value": null, "change_rev": null}, {"name": "fastcan.FastCanBenchmark.track_test_score", "idx": 1, "pretty_name": "fastcan.FastCanBenchmark.track_test_score('classif', 'eta')", "last_rev": 250, "last_value": 0.9222222222222223, "last_err": 0.0, "prev_value": null, "change_rev": null}, {"name": "fastcan.FastCanBenchmark.track_test_score", "idx": 2, "pretty_name": "fastcan.FastCanBenchmark.track_test_score('reg', 'h')", "last_rev": 250, "last_value": 0.9485013694435911, "last_err": 0.0, "prev_value": null, "change_rev": null}, {"name": "fastcan.FastCanBenchmark.track_test_score", "idx": 3, "pretty_name": "fastcan.FastCanBenchmark.track_test_score('reg', 'eta')", "last_rev": 250, "last_value": 0.9485013694435911, "last_err": 0.0, "prev_value": null, "change_rev": null}, {"name": "fastcan.FastCanBenchmark.track_train_score", "idx": 0, "pretty_name": "fastcan.FastCanBenchmark.track_train_score('classif', 'h')", "last_rev": 250, "last_value": 0.891156462585034, "last_err": 0.0, "prev_value": null, "change_rev": null}, {"name": "fastcan.FastCanBenchmark.track_train_score", "idx": 1, "pretty_name": "fastcan.FastCanBenchmark.track_train_score('classif', 'eta')", "last_rev": 250, "last_value": 0.891156462585034, "last_err": 0.0, "prev_value": null, "change_rev": null}, {"name": "fastcan.FastCanBenchmark.track_train_score", "idx": 2, "pretty_name": "fastcan.FastCanBenchmark.track_train_score('reg', 'h')", "last_rev": 250, "last_value": 0.9509396531340139, "last_err": 0.0, "prev_value": null, "change_rev": null}, {"name": "fastcan.FastCanBenchmark.track_train_score", "idx": 3, "pretty_name": "fastcan.FastCanBenchmark.track_train_score('reg', 'eta')", "last_rev": 250, "last_value": 0.9509396531340139, "last_err": 0.0, "prev_value": null, "change_rev": null}, {"name": "narx.NARXBenchmark.peakmem_fit", "idx": 0, "pretty_name": "narx.NARXBenchmark.peakmem_fit('osa')", "last_rev": 250, "last_value": 113029120.0, "last_err": 0.0, "prev_value": null, "change_rev": null}, {"name": "narx.NARXBenchmark.peakmem_fit", "idx": 1, "pretty_name": "narx.NARXBenchmark.peakmem_fit('msa')", "last_rev": 250, "last_value": 113029120.0, "last_err": 0.0, "prev_value": null, "change_rev": null}, {"name": "narx.NARXBenchmark.peakmem_predict", "idx": 0, "pretty_name": "narx.NARXBenchmark.peakmem_predict('osa')", "last_rev": 250, "last_value": 106696704.0, "last_err": 0.0, "prev_value": null, "change_rev": null}, {"name": "narx.NARXBenchmark.peakmem_predict", "idx": 1, "pretty_name": "narx.NARXBenchmark.peakmem_predict('msa')", "last_rev": 250, "last_value": 106696704.0, "last_err": 0.0, "prev_value": null, "change_rev": null}, {"name": "narx.NARXBenchmark.time_fit", "idx": 0, "pretty_name": "narx.NARXBenchmark.time_fit('osa')", "last_rev": 250, "last_value": 0.0025966820000000723, "last_err": 0.0, "prev_value": null, "change_rev": null}, {"name": "narx.NARXBenchmark.time_fit", "idx": 1, "pretty_name": "narx.NARXBenchmark.time_fit('msa')", "last_rev": 250, "last_value": 4.103528512499999, "last_err": 0.0, "prev_value": null, "change_rev": null}, {"name": "narx.NARXBenchmark.time_predict", "idx": 0, "pretty_name": "narx.NARXBenchmark.time_predict('osa')", "last_rev": 250, "last_value": 0.01939444950000535, "last_err": 0.0, "prev_value": null, "change_rev": null}, {"name": "narx.NARXBenchmark.time_predict", "idx": 1, "pretty_name": "narx.NARXBenchmark.time_predict('msa')", "last_rev": 250, "last_value": 0.019442237999996337, "last_err": 0.0, "prev_value": null, "change_rev": null}, {"name": "narx.NARXBenchmark.track_test_score", "idx": 0, "pretty_name": "narx.NARXBenchmark.track_test_score('osa')", "last_rev": 250, "last_value": 0.9317597340303339, "last_err": 0.0, "prev_value": null, "change_rev": null}, {"name": "narx.NARXBenchmark.track_test_score", "idx": 1, "pretty_name": "narx.NARXBenchmark.track_test_score('msa')", "last_rev": 250, "last_value": 0.9317597340303339, "last_err": 0.0, "prev_value": null, "change_rev": null}, {"name": "narx.NARXBenchmark.track_train_score", "idx": 0, "pretty_name": "narx.NARXBenchmark.track_train_score('osa')", "last_rev": 250, "last_value": 0.9975379331320944, "last_err": 0.0, "prev_value": null, "change_rev": null}, {"name": "narx.NARXBenchmark.track_train_score", "idx": 1, "pretty_name": "narx.NARXBenchmark.track_train_score('msa')", "last_rev": 250, "last_value": 0.9975379331320944, "last_err": 0.0, "prev_value": null, "change_rev": null}]